epsilonpolicy/__init__.py
epsilonpolicy/core.py
epsilonpolicy-0.1.1.dist-info/licenses/LICENSE
epsilonpolicy-0.1.1.dist-info/METADATA
epsilonpolicy-0.1.1.dist-info/WHEEL
epsilonpolicy-0.1.1.dist-info/top_level.txt
epsilonpolicy-0.1.1.dist-info/RECORD
