Metadata-Version: 2.4
Name: epsilonpolicy
Version: 0.1.1
Summary: A tiny epsilon-greedy action selection function for reinforcement learning.
Author-email: Salonee Surve <salonee.surve@gmail.com>
License: MIT
Project-URL: Homepage, https://github.com/SaloneeSurve/epsilonpolicy
Keywords: reinforcement-learning,epsilon-greedy,rl
Requires-Python: >=3.8
License-File: LICENSE
Dynamic: license-file
